client/__init__.py
client/main.py
s2c-0.0.7.dist-info/licenses/LICENSE.txt
server/__init__.py
server/main.py
tests/test_camera.py
s2c-0.0.7.dist-info/METADATA
s2c-0.0.7.dist-info/WHEEL
s2c-0.0.7.dist-info/entry_points.txt
s2c-0.0.7.dist-info/top_level.txt
s2c-0.0.7.dist-info/RECORD
