Metadata-Version: 2.4
Name: s2c
Version: 0.0.7
Summary: Secure End to End encrypted video chat over terminal.
Home-page: https://github.com/sanix-darker/s2c
Author: Sanix-Darker
Author-email: Sanix-darker <s4nixd@gmail.com>
License: MIT
Project-URL: Homepage, https://github.com/sanix-darker/s2c
Classifier: Programming Language :: Python :: 3
Classifier: License :: OSI Approved :: MIT License
Classifier: Operating System :: OS Independent
Requires-Python: >=3.10
License-File: LICENSE.txt
Requires-Dist: numpy>=2.2.6
Requires-Dist: opencv-python>=4.11.0.86
Requires-Dist: paramiko>=3.5.1
Requires-Dist: pyaudio>=0.2.14
Requires-Dist: setuptools>=80.9.0
Dynamic: author
Dynamic: home-page
Dynamic: license-file
Dynamic: requires-python
